setup.cfg
setup.py
django_henkou.egg-info/PKG-INFO
django_henkou.egg-info/SOURCES.txt
django_henkou.egg-info/dependency_links.txt
django_henkou.egg-info/entry_points.txt
django_henkou.egg-info/requires.txt
django_henkou.egg-info/top_level.txt
henkou/__init__.py
henkou/admin.py
henkou/apps.py
henkou/models.py
henkou/registry.py
henkou/signals.py
henkou/tests.py
henkou/views.py
henkou/backends/__init__.py
henkou/backends/base.py
henkou/migrations/0001_initial.py
henkou/migrations/__init__.py
tests/__init__.py
tests/example/__init__.py
tests/example/__main__.py
tests/example/settings.py
tests/example/urls.py